Workbook

Sheet Assumptions
A1: Lavender House Cleaning — Pricing Model
A2: Edit the YELLOW cells only. Every price and margin on the other tabs recalculates automatically.
A3: Blue text = input you can change | Black text = calculated formula
A5: LABOR
A6: Cleaner hourly wage | B6: 27
A7: Employer FICA (Social Security + Medicare) | B7: 0.0765
A8: Workers' comp insurance (cleaning trade) | B8: 0.04
A9: Federal + state unemployment (FUTA/SUTA) | B9: 0.02
A10: Paid non-billable hrs per job (drive, setup, restock) | B10: 0.4
A11: PRICING
A12: Target revenue per billable cleaner-hour | B12: 65
A13: COST PER JOB
A14: Cleaning supplies & products | B14: 6
A15: Vehicle & mileage | B15: 8
A16: Liability insurance & bonding (allocated) | B16: 4
A17: Phone, software, marketing (allocated) | B17: 10
A18: Card processing — percent | B18: 0.029
A19: Card processing — flat per transaction | B19: 0.3
A21: CALCULATED
A22: Total payroll burden % | B22: =B7+B8+B9 -> 0.1365
A23: Fully loaded labor cost per hour | B23: =B6*(1+B22) -> 30.6855
A24: Fixed cost per job (before card fees) | B24: =B14+B15+B16+B17 -> 28
A26: ASSUMPTION NOTES
A27: Wage of $27.00/hr set by owner (ORKD) — this model is built backwards from that number.
A28: FICA 7.65% is the statutory employer share. Workers' comp ~4% and FUTA/SUTA ~2% are typical
A29: ranges for janitorial/cleaning payroll in Colorado — confirm with your payroll provider.
A30: Paid non-billable time (0.40 hr/job) covers drive time between jobs, setup and restocking.
A31: Paying this is what makes the job feel stable rather than gig work.
A32: Per-job overhead figures are planning estimates — replace with your real costs once you
A33: have three months of actuals.
A34: Card processing 2.9% + $0.30 is Stripe's standard published US rate.
A35: This model assumes W-2 employees. 1099 contractors remove the ~13.7% burden but
A36: misclassification is heavily enforced in cleaning — talk to an accountant first.

Sheet Job Pricing
A1: Job-by-Job Economics
A2: Menu Price is the only blue input here — change it and margin updates. Hours are your time estimates.
A4: Service | B4: Home Size | C4: Billable Hrs | D4: Menu Price | E4: Cleaner Take-Home | F4: Loaded Labor Cost | G4: Supplies & Overhead | H4: Card Fee | I4: Total Cost | J4: Gross Profit | K4: Margin % | L4: Revenue / Hr
A5: Basic Cleaning | B5: Studio / 1 Bed | C5: 2 | D5: 130 | E5: =(C5+Assumptions!$B$10)*Assumptions!$B$6 -> 64.8 | F5: =(C5+Assumptions!$B$10)*Assumptions!$B$23 -> 73.6452 | G5: =Assumptions!$B$24 -> 28 | H5: =D5*Assumptions!$B$18+Assumptions!$B$19 -> 4.07 | I5: =F5+G5+H5 -> 105.7152 | J5: =D5-I5 -> 24.2848 | K5: =IFERROR(J5/D5,0) -> 0.18680615 | L5: =IFERROR(D5/C5,0) -> 65
A6: Basic Cleaning | B6: 2 Bed | C6: 2.5 | D6: 160 | E6: =(C6+Assumptions!$B$10)*Assumptions!$B$6 -> 78.3 | F6: =(C6+Assumptions!$B$10)*Assumptions!$B$23 -> 88.98795 | G6: =Assumptions!$B$24 -> 28 | H6: =D6*Assumptions!$B$18+Assumptions!$B$19 -> 4.94 | I6: =F6+G6+H6 -> 121.92795 | J6: =D6-I6 -> 38.07205 | K6: =IFERROR(J6/D6,0) -> 0.23795031 | L6: =IFERROR(D6/C6,0) -> 64
A7: Basic Cleaning | B7: 3 Bed | C7: 3 | D7: 195 | E7: =(C7+Assumptions!$B$10)*Assumptions!$B$6 -> 91.8 | F7: =(C7+Assumptions!$B$10)*Assumptions!$B$23 -> 104.3307 | G7: =Assumptions!$B$24 -> 28 | H7: =D7*Assumptions!$B$18+Assumptions!$B$19 -> 5.955 | I7: =F7+G7+H7 -> 138.2857 | J7: =D7-I7 -> 56.7143 | K7: =IFERROR(J7/D7,0) -> 0.29084256 | L7: =IFERROR(D7/C7,0) -> 65
A8: Basic Cleaning | B8: 4 Bed | C8: 3.75 | D8: 245 | E8: =(C8+Assumptions!$B$10)*Assumptions!$B$6 -> 112.05 | F8: =(C8+Assumptions!$B$10)*Assumptions!$B$23 -> 127.34483 | G8: =Assumptions!$B$24 -> 28 | H8: =D8*Assumptions!$B$18+Assumptions!$B$19 -> 7.405 | I8: =F8+G8+H8 -> 162.74982 | J8: =D8-I8 -> 82.250175 | K8: =IFERROR(J8/D8,0) -> 0.335715 | L8: =IFERROR(D8/C8,0) -> 65.333333
A9: Detailed Standard | B9: Studio / 1 Bed | C9: 2.5 | D9: 160 | E9: =(C9+Assumptions!$B$10)*Assumptions!$B$6 -> 78.3 | F9: =(C9+Assumptions!$B$10)*Assumptions!$B$23 -> 88.98795 | G9: =Assumptions!$B$24 -> 28 | H9: =D9*Assumptions!$B$18+Assumptions!$B$19 -> 4.94 | I9: =F9+G9+H9 -> 121.92795 | J9: =D9-I9 -> 38.07205 | K9: =IFERROR(J9/D9,0) -> 0.23795031 | L9: =IFERROR(D9/C9,0) -> 64
A10: Detailed Standard | B10: 2 Bed | C10: 3 | D10: 195 | E10: =(C10+Assumptions!$B$10)*Assumptions!$B$6 -> 91.8 | F10: =(C10+Assumptions!$B$10)*Assumptions!$B$23 -> 104.3307 | G10: =Assumptions!$B$24 -> 28 | H10: =D10*Assumptions!$B$18+Assumptions!$B$19 -> 5.955 | I10: =F10+G10+H10 -> 138.2857 | J10: =D10-I10 -> 56.7143 | K10: =IFERROR(J10/D10,0) -> 0.29084256 | L10: =IFERROR(D10/C10,0) -> 65
A11: Detailed Standard | B11: 3 Bed | C11: 3.75 | D11: 245 | E11: =(C11+Assumptions!$B$10)*Assumptions!$B$6 -> 112.05 | F11: =(C11+Assumptions!$B$10)*Assumptions!$B$23 -> 127.34483 | G11: =Assumptions!$B$24 -> 28 | H11: =D11*Assumptions!$B$18+Assumptions!$B$19 -> 7.405 | I11: =F11+G11+H11 -> 162.74982 | J11: =D11-I11 -> 82.250175 | K11: =IFERROR(J11/D11,0) -> 0.335715 | L11: =IFERROR(D11/C11,0) -> 65.333333
A12: Detailed Standard | B12: 4 Bed | C12: 4.5 | D12: 290 | E12: =(C12+Assumptions!$B$10)*Assumptions!$B$6 -> 132.3 | F12: =(C12+Assumptions!$B$10)*Assumptions!$B$23 -> 150.35895 | G12: =Assumptions!$B$24 -> 28 | H12: =D12*Assumptions!$B$18+Assumptions!$B$19 -> 8.71 | I12: =F12+G12+H12 -> 187.06895 | J12: =D12-I12 -> 102.93105 | K12: =IFERROR(J12/D12,0) -> 0.35493466 | L12: =IFERROR(D12/C12,0) -> 64.444444
A13: Deep Cleaning | B13: Studio / 1 Bed | C13: 3.5 | D13: 230 | E13: =(C13+Assumptions!$B$10)*Assumptions!$B$6 -> 105.3 | F13: =(C13+Assumptions!$B$10)*Assumptions!$B$23 -> 119.67345 | G13: =Assumptions!$B$24 -> 28 | H13: =D13*Assumptions!$B$18+Assumptions!$B$19 -> 6.97 | I13: =F13+G13+H13 -> 154.64345 | J13: =D13-I13 -> 75.35655 | K13: =IFERROR(J13/D13,0) -> 0.32763717 | L13: =IFERROR(D13/C13,0) -> 65.714286
A14: Deep Cleaning | B14: 2 Bed | C14: 4.5 | D14: 290 | E14: =(C14+Assumptions!$B$10)*Assumptions!$B$6 -> 132.3 | F14: =(C14+Assumptions!$B$10)*Assumptions!$B$23 -> 150.35895 | G14: =Assumptions!$B$24 -> 28 | H14: =D14*Assumptions!$B$18+Assumptions!$B$19 -> 8.71 | I14: =F14+G14+H14 -> 187.06895 | J14: =D14-I14 -> 102.93105 | K14: =IFERROR(J14/D14,0) -> 0.35493466 | L14: =IFERROR(D14/C14,0) -> 64.444444
A15: Deep Cleaning | B15: 3 Bed | C15: 5.5 | D15: 360 | E15: =(C15+Assumptions!$B$10)*Assumptions!$B$6 -> 159.3 | F15: =(C15+Assumptions!$B$10)*Assumptions!$B$23 -> 181.04445 | G15: =Assumptions!$B$24 -> 28 | H15: =D15*Assumptions!$B$18+Assumptions!$B$19 -> 10.74 | I15: =F15+G15+H15 -> 219.78445 | J15: =D15-I15 -> 140.21555 | K15: =IFERROR(J15/D15,0) -> 0.38948764 | L15: =IFERROR(D15/C15,0) -> 65.454545
A16: Deep Cleaning | B16: 4 Bed | C16: 6.5 | D16: 420 | E16: =(C16+Assumptions!$B$10)*Assumptions!$B$6 -> 186.3 | F16: =(C16+Assumptions!$B$10)*Assumptions!$B$23 -> 211.72995 | G16: =Assumptions!$B$24 -> 28 | H16: =D16*Assumptions!$B$18+Assumptions!$B$19 -> 12.48 | I16: =F16+G16+H16 -> 252.20995 | J16: =D16-I16 -> 167.79005 | K16: =IFERROR(J16/D16,0) -> 0.39950012 | L16: =IFERROR(D16/C16,0) -> 64.615385
... A23: AirBnB Turnover | B23: 3 Bed+ | C23: 2.5 | D23: 180 | E23: =(C23+Assumptions!$B$10)*Assumptions!$B$6 -> 78.3 | F23: =(C23+Assumptions!$B$10)*Assumptions!$B$23 -> 88.98795 | G23: =Assumptions!$B$24 -> 28 | H23: =D23*Assumptions!$B$18+Assumptions!$B$19 -> 5.52 | I23: =F23+G23+H23 -> 122.50795 | J23: =D23-I23 -> 57.49205 | K23: =IFERROR(J23/D23,0) -> 0.31940028 | L23: =IFERROR(D23/C23,0) -> 72
A24: TOTALS / AVERAGE | C24: =SUM(C5:C23) -> 73 | D24: =SUM(D5:D23) -> 4805 | J24: =SUM(J5:J23) -> 1654.7037 | K24: =IFERROR(J24/D24,0) -> 0.34437122
A26: Every row must stay profitable. If Margin % drops below ~15%, raise the Menu Price or trim the hours.
A27: Cleaner Take-Home is gross pay to the cleaner (wage x billable + paid drive time), before their own taxes.

Sheet Add-Ons
A1: Add-On Pricing
A2: Add-ons ride on an existing job, so there is no extra drive time, vehicle or overhead cost — only labor.
A4: Add-On Service | B4: Hours | C4: Price | D4: Loaded Labor Cost | E4: Gross Profit | F4: Margin %
A5: Oven deep clean (inside) | B5: 0.6 | C5: 40 | D5: =B5*Assumptions!$B$23 -> 18.4113 | E5: =C5-D5 -> 21.5887 | F5: =IFERROR(E5/C5,0) -> 0.5397175
A6: Bathroom deep scrub, per bathroom | B6: 0.55 | C6: 35 | D6: =B6*Assumptions!$B$23 -> 16.877025 | E6: =C6-D6 -> 18.122975 | F6: =IFERROR(E6/C6,0) -> 0.51779929
A7: Inside refrigerator | B7: 0.5 | C7: 35 | D7: =B7*Assumptions!$B$23 -> 15.34275 | E7: =C7-D7 -> 19.65725 | F7: =IFERROR(E7/C7,0) -> 0.56163571
A8: Inside cabinets | B8: 0.65 | C8: 40 | D8: =B8*Assumptions!$B$23 -> 19.945575 | E8: =C8-D8 -> 20.054425 | F8: =IFERROR(E8/C8,0) -> 0.50136063
A9: Interior windows | B9: 0.75 | C9: 50 | D9: =B9*Assumptions!$B$23 -> 23.014125 | E9: =C9-D9 -> 26.985875 | F9: =IFERROR(E9/C9,0) -> 0.5397175
A10: Laundry, per load (wash/dry/fold) | B10: 0.35 | C10: 25 | D10: =B10*Assumptions!$B$23 -> 10.739925 | E10: =C10-D10 -> 14.260075 | F10: =IFERROR(E10/C10,0) -> 0.570403
A11: Garage or patio sweep | B11: 0.5 | C11: 35 | D11: =B11*Assumptions!$B$23 -> 15.34275 | E11: =C11-D11 -> 19.65725 | F11: =IFERROR(E11/C11,0) -> 0.56163571
A12: Dishes washed | B12: 0.35 | C12: 25 | D12: =B12*Assumptions!$B$23 -> 10.739925 | E12: =C12-D12 -> 14.260075 | F12: =IFERROR(E12/C12,0) -> 0.570403
A13: Organization, per hour | B13: 1 | C13: 65 | D13: =B13*Assumptions!$B$23 -> 30.6855 | E13: =C13-D13 -> 34.3145 | F13: =IFERROR(E13/C13,0) -> 0.52791538
A15: Add-ons carry the best margin in the business — always offer them at booking.

Sheet Cleaner Pay
A1: What a Cleaner Actually Earns
A2: Use this when recruiting — real numbers beat vague promises.
A4: Billable hours guaranteed per week | B4: 32
A5: Paid non-billable hours per week (drive/setup) | B5: =B4/3.8*Assumptions!$B$10 -> 3.3684211
A6: Total paid hours per week | B6: =B4+B5 -> 35.368421
A7: Gross pay per week | B7: =B6*Assumptions!$B$6 -> 954.94737
A8: Gross pay per month | B8: =B7*52/12 -> 4138.1053
A9: Gross pay per year | B9: =B7*52 -> 49657.263
A10: Employer cost per year (wage + burden) | B10: =B6*52*Assumptions!$B$23 -> 56435.48
A12: STABILITY COMMITMENTS TO ADVERTISE
A13: • $27/hour — well above the Pueblo market rate for cleaners
A14: • Guaranteed minimum weekly hours, so income is predictable
A15: • Paid drive time between jobs — cleaners are not working for free between houses
A16: • Weekly pay, every Friday
A17: • All supplies and equipment provided — no out-of-pocket costs
A18: • Same-day cancellations by a client are still paid (protects the cleaner, not just the business)
A19: • Consider adding after 90 days: paid time off, mileage reimbursement, a health stipend
A21: Note: these are business planning figures, not legal or tax advice. Confirm wage, classification and
A22: insurance requirements with a Colorado accountant or employment attorney before hiring.

Sheet Business Outlook
A1: Business Outlook
A2: Rough projection at full schedules. Change the cleaner count and hours to model growth.
A4: Number of cleaners on staff | B4: 3
A5: Billable hours per cleaner per week | B5: ='Cleaner Pay'!B4 -> 32
A6: Average revenue per billable hour | B6: =IFERROR('Job Pricing'!D24/'Job Pricing'!C24,0) -> 65.821918
A7: Average gross margin | B7: ='Job Pricing'!K24 -> 0.34437122
A9: Weekly revenue | B9: =B4*B5*B6 -> 6318.9041
A10: Weekly gross profit | B10: =B9*B7 -> 2176.0487
A11: Annual revenue | B11: =B9*52 -> 328583.01
A12: Annual gross profit (before owner pay & fixed costs) | B12: =B10*52 -> 113154.53
A14: Gross profit still has to cover: your own salary, office/storage, accounting, licensing,
A15: advertising beyond the allocated per-job amount, equipment replacement, and taxes.
A16: Treat annual gross profit as the ceiling on owner income, not the take-home.
